bolides_bounding_box/__init__.py
bolides_bounding_box/bolide.py
bolides_bounding_box/bounding_box.py
bolides_bounding_box/utils.py
bolides_bounding_box-0.0.8.dist-info/LICENSE
bolides_bounding_box-0.0.8.dist-info/METADATA
bolides_bounding_box-0.0.8.dist-info/WHEEL
bolides_bounding_box-0.0.8.dist-info/top_level.txt
bolides_bounding_box-0.0.8.dist-info/RECORD
