Metadata-Version: 2.1
Name: bolides-bounding-box
Version: 0.0.8
Summary: A package to get bounding box images from GOES satellites.
Home-page: http://pypi.python.org/pypi/bolides-bounding-box/
Author: yajucb
Author-email: yajucb@berkely.edu
License: LICENSE.txt
Platform: UNKNOWN
License-File: LICENSE
Requires-Dist: requests
Requires-Dist: numpy
Requires-Dist: pyproj
Requires-Dist: shapely
Requires-Dist: matplotlib
Requires-Dist: cartopy
Requires-Dist: boto3
Requires-Dist: netCDF4
